flask_gopher/__init__.py
flask_gopher/__version__.py
flask_gopher/flask_gopher.py
Flask_Gopher-3.0.0.dist-info/LICENSE
Flask_Gopher-3.0.0.dist-info/METADATA
Flask_Gopher-3.0.0.dist-info/WHEEL
Flask_Gopher-3.0.0.dist-info/top_level.txt
Flask_Gopher-3.0.0.dist-info/RECORD
