Metadata-Version: 2.1
Name: Flask-Gopher
Version: 3.0.0
Summary: A Flask extension to support the Gopher Protocol
Home-page: https://github.com/michael-lazar/flask-gopher
Author: Michael Lazar
Author-email: lazar.michael22@gmail.com
License: GPL-3.0
Platform: any
Classifier: Environment :: Web Environment
Classifier: Intended Audience :: Developers
Classifier: License :: OSI Approved :: GNU General Public License v3 (GPLv3)
Classifier: Operating System :: OS Independent
Classifier: Programming Language :: Python
Classifier: Programming Language :: Python :: 3
Classifier: Topic :: Internet :: WWW/HTTP :: Dynamic Content
Classifier: Topic :: Software Development :: Libraries :: Python Modules
License-File: LICENSE
Requires-Dist: Flask (>=2.1)
Requires-Dist: pyfiglet (<=0.7.6)
Requires-Dist: tabulate
Requires-Dist: pyopenssl
Provides-Extra: test
Requires-Dist: pytest ; extra == 'test'
Requires-Dist: mypy ; extra == 'test'
Requires-Dist: types-tabulate ; extra == 'test'
